README.md
app.py
examples/basic.md
examples/file.md
examples/input.md
examples/playwright.md
examples/stream.md
examples/sudo.md
examples/table.md
src/__init__.py
src/config.py
src/executor.py
src/helpers.py
src/requests.py
src/runner.py
src/static.py
src/execute/file_block.py
src/execute/run_block.py
src/file_manager/__init__.py
src/file_manager/directory.py
src/file_manager/file.py
static/index.html
static/assets/index-7EBogIFR.css
static/assets/index-CGDnuYMv.js
static/assets/vendor-DwFj1DrT.js
rundmark-0.2.1.dist-info/METADATA
rundmark-0.2.1.dist-info/WHEEL
rundmark-0.2.1.dist-info/entry_points.txt
rundmark-0.2.1.dist-info/RECORD
