Metadata-Version: 2.4
Name: rundmark
Version: 0.2.1
Summary: Run document of Markdown
Requires-Python: >=3.9
Requires-Dist: fastapi==0.104.1
Requires-Dist: python-multipart>=0.0.20
Requires-Dist: requests>=2.32.5
Requires-Dist: uvicorn[standard]==0.24.0
